telegram_pm/__init__.py
telegram_pm/config.py
telegram_pm/database/__init__.py
telegram_pm/database/csv_processor.py
telegram_pm/database/sqlite_processor.py
telegram_pm/entities.py
telegram_pm/http_client/__init__.py
telegram_pm/http_client/client.py
telegram_pm/parsers/__init__.py
telegram_pm/parsers/base.py
telegram_pm/parsers/post.py
telegram_pm/parsers/preview.py
telegram_pm/parsers/tag_options.py
telegram_pm/run.py
telegram_pm/utils/__init__.py
telegram_pm/utils/logger.py
telegram_pm/utils/parse.py
telegram_pm/utils/url.py
telegram_pm-0.1.5.dist-info/entry_points.txt
telegram_pm-0.1.5.dist-info/LICENSE
telegram_pm-0.1.5.dist-info/METADATA
telegram_pm-0.1.5.dist-info/WHEEL
telegram_pm-0.1.5.dist-info/RECORD
