Metadata-Version: 2.3
Name: telegram-pm
Version: 0.1.5
Summary: Telegram preview page parser
Author: Your Name
Author-email: you@example.com
Requires-Python: >=3.12
Classifier: Programming Language :: Python :: 3
Classifier: Programming Language :: Python :: 3.12
Classifier: Programming Language :: Python :: 3.13
Requires-Dist: aiosqlite (>=0.21.0,<0.22.0)
Requires-Dist: bs4 (>=0.0.2,<0.0.3)
Requires-Dist: html5lib (>=1.1,<2.0)
Requires-Dist: httpx (>=0.28.1,<0.29.0)
Requires-Dist: python-dotenv (>=1.1.0,<2.0.0)
Requires-Dist: retry (>=0.9.2,<0.10.0)
Requires-Dist: structlog (>=25.2.0,<26.0.0)
Requires-Dist: typer (>=0.15.2,<0.16.0)
